AUTHORS.rst
CHANGELOG.rst
LICENSE
MANIFEST.in
README.rst
requirements.txt
setup.py
pyllegro/__init__.py
pyllegro/core.py
pyllegro.egg-info/PKG-INFO
pyllegro.egg-info/SOURCES.txt
pyllegro.egg-info/dependency_links.txt
pyllegro.egg-info/requires.txt
pyllegro.egg-info/top_level.txt