Metadata-Version: 1.1
Name: pyllegro
Version: 0.0.1
Summary: pyllegro is a simple python wrapper for allegro api.
Home-page: https://github.com/oczkers/pyllegro
Author: Piotr Staroszczyk
Author-email: piotr.staroszczyk@get24.org
License: GNU LGPL v3
Download-URL: https://github.com/oczkers/pyllegro/releases
Keywords: pyllegro allegro api webapi wrapper
Platform: any
Classifier: Development Status :: 3 - Alpha
Classifier: Intended Audience :: Developers
Classifier: Natural Language :: English
Classifier: License :: OSI Approved :: GNU Lesser General Public License v3 or later (LGPLv3+)
Classifier: Programming Language :: Python
Classifier: Programming Language :: Python :: 2.6
Classifier: Programming Language :: Python :: 2.7
Classifier: Programming Language :: Python :: 3
Classifier: Programming Language :: Python :: 3.2
Classifier: Programming Language :: Python :: 3.3
Classifier: Programming Language :: Python :: 3.4
Classifier: Programming Language :: Python :: 3.5
Classifier: Programming Language :: Python :: Implementation :: PyPy
Classifier: Topic :: Internet :: WWW/HTTP :: Site Management
Classifier: Topic :: Software Development :: Libraries :: Python Modules
